LICENSE
README.md
setup.py
user_service.egg-info/PKG-INFO
user_service.egg-info/SOURCES.txt
user_service.egg-info/dependency_links.txt
user_service.egg-info/requires.txt
user_service.egg-info/top_level.txt
user_service/users/__init__.py
user_service/users/config/__init__.py
user_service/users/model/__init__.py
user_service/users/model/api.py
user_service/users/model/models.py
user_service/users/model/migrate_repo/__init__.py
user_service/users/model/migrate_repo/env.py
user_service/users/model/migrate_repo/versions/001_create_users_table.py
user_service/users/model/migrate_repo/versions/__init__.py
user_service/users/repository/__init__.py
user_service/users/repository/user.py
user_service/users/repository/user_repository.py
user_service/users/router/__init__.py
user_service/users/router/main.py
user_service/users/service/__init__.py
user_service/users/service/login_service.py
user_service/users/service/register_service.py
user_service/users/tests/__init__.py
user_service/users/tests/config/__init__.py
user_service/users/tests/config/test_user_service.py
user_service/users/tests/model/__init__.py
user_service/users/tests/repository/__init__.py
user_service/users/tests/router/__init__.py
user_service/users/tests/router/main.py
user_service/users/tests/service/__init__.py
user_service/users/tests/utils/__init__.py
user_service/users/user_exceptions/__init__.py
user_service/users/utils/__init__.py