Metadata-Version: 2.1
Name: user-service
Version: 1.0.14
Summary: user service pip package
License-File: LICENSE
